epub_chapterize/__init__.py
epub_chapterize/chapterize.py
epubchapterize-0.1.7.dist-info/licenses/LICENSE
epubchapterize-0.1.7.dist-info/METADATA
epubchapterize-0.1.7.dist-info/WHEEL
epubchapterize-0.1.7.dist-info/entry_points.txt
epubchapterize-0.1.7.dist-info/top_level.txt
epubchapterize-0.1.7.dist-info/RECORD
